gpu_benchmark/__init__.py
gpu_benchmark/ai_cost_benchmark.py
gpu_benchmark/benchmark.py
gpu_benchmark/cli.py
gpu_benchmark/diagnostics.py
gpu_benchmark/monitor.py
gpu_benchmark/scoring.py
gpu_benchmark/utils.py
gpu_benchmark/version.py
gpu_benchmark/application/__init__.py
gpu_benchmark/application/di/__init__.py
gpu_benchmark/application/di/container.py
gpu_benchmark/application/di/providers.py
gpu_benchmark/application/use_cases/__init__.py
gpu_benchmark/application/use_cases/assess_gpu_health.py
gpu_benchmark/application/use_cases/monitor_gpu.py
gpu_benchmark/application/use_cases/run_ai_cost_benchmark.py
gpu_benchmark/application/use_cases/run_benchmark.py
gpu_benchmark/application/use_cases/run_diagnostics.py
gpu_benchmark/backends/__init__.py
gpu_benchmark/backends/amd.py
gpu_benchmark/backends/base.py
gpu_benchmark/backends/intel.py
gpu_benchmark/backends/mock.py
gpu_benchmark/backends/nvidia.py
gpu_benchmark/docker/__init__.py
gpu_benchmark/domain/__init__.py
gpu_benchmark/domain/error_handling/__init__.py
gpu_benchmark/domain/error_handling/error_boundary.py
gpu_benchmark/domain/error_handling/error_types.py
gpu_benchmark/domain/error_handling/fallback_strategies.py
gpu_benchmark/domain/models/__init__.py
gpu_benchmark/domain/models/ai_workload.py
gpu_benchmark/domain/models/benchmark_result.py
gpu_benchmark/domain/models/configuration.py
gpu_benchmark/domain/models/gpu_device.py
gpu_benchmark/domain/models/health_score.py
gpu_benchmark/domain/models/stress_test.py
gpu_benchmark/domain/repositories/__init__.py
gpu_benchmark/domain/repositories/benchmark_repository.py
gpu_benchmark/domain/repositories/configuration_repository.py
gpu_benchmark/domain/repositories/gpu_repository.py
gpu_benchmark/domain/services/__init__.py
gpu_benchmark/domain/services/health_scoring_service.py
gpu_benchmark/infrastructure/__init__.py
gpu_benchmark/infrastructure/adapters/__init__.py
gpu_benchmark/infrastructure/adapters/gpu_backend_adapter.py
gpu_benchmark_tool-0.6.5.dist-info/METADATA
gpu_benchmark_tool-0.6.5.dist-info/WHEEL
gpu_benchmark_tool-0.6.5.dist-info/entry_points.txt
gpu_benchmark_tool-0.6.5.dist-info/top_level.txt
gpu_benchmark_tool-0.6.5.dist-info/RECORD
