Metadata-Version: 2.4
Name: gpu-benchmark-tool
Version: 0.6.5
Summary: Multi-vendor GPU health monitoring supporting old GPUs for e-waste reduction
Home-page: https://github.com/yourusername/gpu-benchmark-tool
Author: Yousuf Rajput
Author-email: Yousuf Rajput <ywrajput@gmail.com>
Project-URL: Homepage, https://github.com/ywrajput/gpu-benchmark-tool
Project-URL: Repository, https://github.com/ywrajput/gpu-benchmark-tool
Project-URL: Issues, https://github.com/ywrajput/gpu-benchmark-tool/issues
Keywords: gpu,benchmark,monitoring,cuda,rocm,intel,nvidia,amd,old-gpu,ewaste,recycling,sustainability
Classifier: Development Status :: 4 - Beta
Classifier: Intended Audience :: Developers
Classifier: Intended Audience :: System Administrators
Classifier: Intended Audience :: Science/Research
Classifier: Topic :: System :: Hardware
Classifier: Topic :: System :: Monitoring
Classifier: Topic :: Scientific/Engineering :: Artificial Intelligence
Classifier: License :: OSI Approved :: MIT License
Classifier: Programming Language :: Python :: 3
Classifier: Programming Language :: Python :: 3.8
Classifier: Programming Language :: Python :: 3.9
Classifier: Programming Language :: Python :: 3.10
Classifier: Programming Language :: Python :: 3.11
Classifier: Programming Language :: Python :: 3.12
Classifier: Operating System :: OS Independent
Requires-Python: >=3.8
Requires-Dist: numpy>=1.21.0
Requires-Dist: psutil>=5.8.0
Requires-Dist: pyyaml>=6.0
Requires-Dist: torch>=2.0.0
Provides-Extra: nvidia
Requires-Dist: nvidia-ml-py>=11.450.51; extra == "nvidia"
Requires-Dist: onnxruntime-gpu>=1.15.0; extra == "nvidia"
Provides-Extra: amd
Provides-Extra: intel
Requires-Dist: intel-extension-for-pytorch>=2.0.0; extra == "intel"
Provides-Extra: all
Requires-Dist: nvidia-ml-py>=11.450.51; extra == "all"
Requires-Dist: intel-extension-for-pytorch>=2.0.0; extra == "all"
Requires-Dist: docker>=6.0.0; extra == "all"
Provides-Extra: dev
Requires-Dist: pytest>=7.0; extra == "dev"
Requires-Dist: ruff>=0.1.0; extra == "dev"
Requires-Dist: mypy>=0.900; extra == "dev"
Requires-Dist: build>=0.10.0; extra == "dev"
Requires-Dist: twine>=4.0.2; extra == "dev"
Dynamic: author
Dynamic: home-page
Dynamic: requires-python
